python2x3.py
bloom_filter/__init__.py
bloom_filter/bloom_filter.py
bloom_filter-1.3.3.dist-info/AUTHORS.md
bloom_filter-1.3.3.dist-info/METADATA
bloom_filter-1.3.3.dist-info/WHEEL
bloom_filter-1.3.3.dist-info/top_level.txt
bloom_filter-1.3.3.dist-info/RECORD
