Metadata-Version: 2.1
Name: bloom-filter
Version: 1.3.3
Summary: Pure Python Bloom Filter module
Home-page: https://github.com/hiway/python-bloom-filter
Author: Harshad Sharma
Author-email: harshad@sharma.io
License: MIT
Keywords: probabilistic set datastructure
Platform: Cross platform
Classifier: Development Status :: 5 - Production/Stable
Classifier: Intended Audience :: Developers
Classifier: Programming Language :: Python :: 2
Classifier: Programming Language :: Python :: 3
License-File: AUTHORS.md
